<?xml version="1.0" encoding="UTF-8"?>
<soapenv:Envelope xmlns:soapenv="http://schemas.xmlsoap.org/soap/envelope/" xmlns="urn:partner.soap.sforce.com" xmlns:sf="urn:sobject.partner.soap.sforce.com" xmlns:xsi="http://www.w3.org/2001/XMLSchema-instance"><soapenv:Header><LimitInfoHeader><limitInfo><current>37</current><limit>15000</limit><type>API REQUESTS</type></limitInfo></LimitInfoHeader></soapenv:Header><soapenv:Body><retrieveResponse><result xsi:type="sf:sObject"><sf:type>ApexClass</sf:type><sf:Id>01p2800000EmQxcAAF</sf:Id><sf:ApiVersion>34.0</sf:ApiVersion><sf:Body>(hidden)</sf:Body><sf:BodyCrc>-1</sf:BodyCrc><sf:CreatedById>00528000003pbOYAAY</sf:CreatedById><sf:CreatedDate>2017-01-23T15:10:11.000Z</sf:CreatedDate><sf:Id>01p2800000EmQxcAAF</sf:Id><sf:IsValid>true</sf:IsValid><sf:LastModifiedById>00528000003pbOYAAY</sf:LastModifiedById><sf:LastModifiedDate>2017-01-23T15:10:11.000Z</sf:LastModifiedDate><sf:LengthWithoutComments>-1</sf:LengthWithoutComments><sf:Name>FloDocsLinksController</sf:Name><sf:NamespacePrefix>FLODocs</sf:NamespacePrefix><sf:Status>Active</sf:Status><sf:SystemModstamp>2017-04-25T16:18:45.000Z</sf:SystemModstamp></result><result xsi:type="sf:sObject"><sf:type>ApexClass</sf:type><sf:Id>01p2800000EmQxaAAF</sf:Id><sf:ApiVersion>34.0</sf:ApiVersion><sf:Body>(hidden)</sf:Body><sf:BodyCrc>-1</sf:BodyCrc><sf:CreatedById>00528000003pbOYAAY</sf:CreatedById><sf:CreatedDate>2017-01-23T15:10:11.000Z</sf:CreatedDate><sf:Id>01p2800000EmQxaAAF</sf:Id><sf:IsValid>true</sf:IsValid><sf:LastModifiedById>00528000003pbOYAAY</sf:LastModifiedById><sf:LastModifiedDate>2017-01-23T15:10:11.000Z</sf:LastModifiedDate><sf:LengthWithoutComments>-1</sf:LengthWithoutComments><sf:Name>FloDemoCoverage</sf:Name><sf:NamespacePrefix>FLODocs</sf:NamespacePrefix><sf:Status>Active</sf:Status><sf:SystemModstamp>2017-04-25T16:18:45.000Z</sf:SystemModstamp></result><result xsi:type="sf:sObject"><sf:type>ApexClass</sf:type><sf:Id>01p2800000EmQxoAAF</sf:Id><sf:ApiVersion>34.0</sf:ApiVersion><sf:Body>(hidden)</sf:Body><sf:BodyCrc>-1</sf:BodyCrc><sf:CreatedById>00528000003pbOYAAY</sf:CreatedById><sf:CreatedDate>2017-01-23T15:10:12.000Z</sf:CreatedDate><sf:Id>01p2800000EmQxoAAF</sf:Id><sf:IsValid>true</sf:IsValid><sf:LastModifiedById>00528000003pbOYAAY</sf:LastModifiedById><sf:LastModifiedDate>2017-01-23T15:10:12.000Z</sf:LastModifiedDate><sf:LengthWithoutComments>-1</sf:LengthWithoutComments><sf:Name>FloMakeJoinHandlerClass</sf:Name><sf:NamespacePrefix>FLODocs</sf:NamespacePrefix><sf:Status>Active</sf:Status><sf:SystemModstamp>2017-04-25T16:18:45.000Z</sf:SystemModstamp></result><result xsi:type="sf:sObject"><sf:type>ApexClass</sf:type><sf:Id>01p2800000EmQxUAAV</sf:Id><sf:ApiVersion>36.0</sf:ApiVersion><sf:Body>(hidden)</sf:Body><sf:BodyCrc>-1</sf:BodyCrc><sf:CreatedById>00528000003pbOYAAY</sf:CreatedById><sf:CreatedDate>2017-01-23T15:10:11.000Z</sf:CreatedDate><sf:Id>01p2800000EmQxUAAV</sf:Id><sf:IsValid>true</sf:IsValid><sf:LastModifiedById>00528000003pbOYAAY</sf:LastModifiedById><sf:LastModifiedDate>2017-01-23T15:10:11.000Z</sf:LastModifiedDate><sf:LengthWithoutComments>-1</sf:LengthWithoutComments><sf:Name>FloChangeRequestEditNewControllerTest</sf:Name><sf:NamespacePrefix>FLODocs</sf:NamespacePrefix><sf:Status>Active</sf:Status><sf:SystemModstamp>2017-04-25T16:18:45.000Z</sf:SystemModstamp></result><result xsi:type="sf:sObject"><sf:type>ApexClass</sf:type><sf:Id>01p2800000EmQy1AAF</sf:Id><sf:ApiVersion>34.0</sf:ApiVersion><sf:Body>(hidden)</sf:Body><sf:BodyCrc>-1</sf:BodyCrc><sf:CreatedById>00528000003pbOYAAY</sf:CreatedById><sf:CreatedDate>2017-01-23T15:10:12.000Z</sf:CreatedDate><sf:Id>01p2800000EmQy1AAF</sf:Id><sf:IsValid>true</sf:IsValid><sf:LastModifiedById>00528000003pbOYAAY</sf:LastModifiedById><sf:LastModifiedDate>2017-01-23T15:10:12.000Z</sf:LastModifiedDate><sf:LengthWithoutComments>-1</sf:LengthWithoutComments><sf:Name>FloReScannerInitJob</sf:Name><sf:NamespacePrefix>FLODocs</sf:NamespacePrefix><sf:Status>Active</sf:Status><sf:SystemModstamp>2017-04-25T16:18:47.000Z</sf:SystemModstamp></result><result xsi:type="sf:sObject"><sf:type>ApexClass</sf:type><sf:Id>01p2800000EmQyEAAV</sf:Id><sf:ApiVersion>34.0</sf:ApiVersion><sf:Body>(hidden)</sf:Body><sf:BodyCrc>-1</sf:BodyCrc><sf:CreatedById>00528000003pbOYAAY</sf:CreatedById><sf:CreatedDate>2017-01-23T15:10:13.000Z</sf:CreatedDate><sf:Id>01p2800000EmQyEAAV</sf:Id><sf:IsValid>true</sf:IsValid><sf:LastModifiedById>00528000003pbOYAAY</sf:LastModifiedById><sf:LastModifiedDate>2017-01-23T15:10:13.000Z</sf:LastModifiedDate><sf:LengthWithoutComments>-1</sf:LengthWithoutComments><sf:Name>FloZippex</sf:Name><sf:NamespacePrefix>FLODocs</sf:NamespacePrefix><sf:Status>Active</sf:Status><sf:SystemModstamp>2017-04-25T16:18:47.000Z</sf:SystemModstamp></result><result xsi:type="sf:sObject"><sf:type>ApexClass</sf:type><sf:Id>01p2800000EmQxzAAF</sf:Id><sf:ApiVersion>36.0</sf:ApiVersion><sf:Body>(hidden)</sf:Body><sf:BodyCrc>-1</sf:BodyCrc><sf:CreatedById>00528000003pbOYAAY</sf:CreatedById><sf:CreatedDate>2017-01-23T15:10:12.000Z</sf:CreatedDate><sf:Id>01p2800000EmQxzAAF</sf:Id><sf:IsValid>true</sf:IsValid><sf:LastModifiedById>00528000003pbOYAAY</sf:LastModifiedById><sf:LastModifiedDate>2017-01-23T15:10:12.000Z</sf:LastModifiedDate><sf:LengthWithoutComments>-1</sf:LengthWithoutComments><sf:Name>FloProcessIssueEditNewControllerTest</sf:Name><sf:NamespacePrefix>FLODocs</sf:NamespacePrefix><sf:Status>Active</sf:Status><sf:SystemModstamp>2017-04-25T16:18:47.000Z</sf:SystemModstamp></result><result xsi:type="sf:sObject"><sf:type>ApexClass</sf:type><sf:Id>01p2800000EmN6YAAV</sf:Id><sf:ApiVersion>38.0</sf:ApiVersion><sf:Body>public class TestClassUsingClass implements TestInterface{
    public String testMethodA() {
        TestClass x = new TestClass();
        return TestStaticUtils.TEST;
    }
}</sf:Body><sf:BodyCrc>5.91823536E8</sf:BodyCrc><sf:CreatedById>00528000003pbOYAAY</sf:CreatedById><sf:CreatedDate>2017-01-17T09:29:34.000Z</sf:CreatedDate><sf:Id>01p2800000EmN6YAAV</sf:Id><sf:IsValid>true</sf:IsValid><sf:LastModifiedById>00528000003pbOYAAY</sf:LastModifiedById><sf:LastModifiedDate>2017-01-17T09:32:06.000Z</sf:LastModifiedDate><sf:LengthWithoutComments>177</sf:LengthWithoutComments><sf:Name>TestClassUsingClass</sf:Name><sf:NamespacePrefix xsi:nil="true"/><sf:Status>Active</sf:Status><sf:SystemModstamp>2017-04-25T16:18:48.000Z</sf:SystemModstamp></result><result xsi:type="sf:sObject"><sf:type>ApexClass</sf:type><sf:Id>01p2800000EmQxMAAV</sf:Id><sf:ApiVersion>34.0</sf:ApiVersion><sf:Body>/*
This file is generated and isn't the actual source code for this
managed global class.
This read-only file shows the class's global constructors,
methods, variables, and properties.
To enable code to compile, all methods return null.
*/
global class FLODocsPostInstall implements System.InstallHandler {
    global FLODocsPostInstall() {

    }
    global void onInstall(System.InstallContext ctx) {

    }
}
</sf:Body><sf:BodyCrc>-1</sf:BodyCrc><sf:CreatedById>00528000003pbOYAAY</sf:CreatedById><sf:CreatedDate>2017-01-23T15:10:11.000Z</sf:CreatedDate><sf:Id>01p2800000EmQxMAAV</sf:Id><sf:IsValid>true</sf:IsValid><sf:LastModifiedById>00528000003pbOYAAY</sf:LastModifiedById><sf:LastModifiedDate>2017-01-23T15:10:11.000Z</sf:LastModifiedDate><sf:LengthWithoutComments>-1</sf:LengthWithoutComments><sf:Name>FLODocsPostInstall</sf:Name><sf:NamespacePrefix>FLODocs</sf:NamespacePrefix><sf:Status>Active</sf:Status><sf:SystemModstamp>2017-04-25T16:18:45.000Z</sf:SystemModstamp></result><result xsi:type="sf:sObject"><sf:type>ApexClass</sf:type><sf:Id>01p2800000EmQxXAAV</sf:Id><sf:ApiVersion>34.0</sf:ApiVersion><sf:Body>(hidden)</sf:Body><sf:BodyCrc>-1</sf:BodyCrc><sf:CreatedById>00528000003pbOYAAY</sf:CreatedById><sf:CreatedDate>2017-01-23T15:10:11.000Z</sf:CreatedDate><sf:Id>01p2800000EmQxXAAV</sf:Id><sf:IsValid>true</sf:IsValid><sf:LastModifiedById>00528000003pbOYAAY</sf:LastModifiedById><sf:LastModifiedDate>2017-01-23T15:10:11.000Z</sf:LastModifiedDate><sf:LengthWithoutComments>-1</sf:LengthWithoutComments><sf:Name>FloCleanMakeJoinDate</sf:Name><sf:NamespacePrefix>FLODocs</sf:NamespacePrefix><sf:Status>Active</sf:Status><sf:SystemModstamp>2017-04-25T16:18:45.000Z</sf:SystemModstamp></result><result xsi:type="sf:sObject"><sf:type>ApexClass</sf:type><sf:Id>01p2800000EmQxuAAF</sf:Id><sf:ApiVersion>36.0</sf:ApiVersion><sf:Body>(hidden)</sf:Body><sf:BodyCrc>-1</sf:BodyCrc><sf:CreatedById>00528000003pbOYAAY</sf:CreatedById><sf:CreatedDate>2017-01-23T15:10:12.000Z</sf:CreatedDate><sf:Id>01p2800000EmQxuAAF</sf:Id><sf:IsValid>true</sf:IsValid><sf:LastModifiedById>00528000003pbOYAAY</sf:LastModifiedById><sf:LastModifiedDate>2017-01-23T15:10:12.000Z</sf:LastModifiedDate><sf:LengthWithoutComments>-1</sf:LengthWithoutComments><sf:Name>FloMultiSelectListControllerTest</sf:Name><sf:NamespacePrefix>FLODocs</sf:NamespacePrefix><sf:Status>Active</sf:Status><sf:SystemModstamp>2017-04-25T16:18:46.000Z</sf:SystemModstamp></result><result xsi:type="sf:sObject"><sf:type>ApexClass</sf:type><sf:Id>01p2800000EmQxVAAV</sf:Id><sf:ApiVersion>34.0</sf:ApiVersion><sf:Body>(hidden)</sf:Body><sf:BodyCrc>-1</sf:BodyCrc><sf:CreatedById>00528000003pbOYAAY</sf:CreatedById><sf:CreatedDate>2017-01-23T15:10:11.000Z</sf:CreatedDate><sf:Id>01p2800000EmQxVAAV</sf:Id><sf:IsValid>true</sf:IsValid><sf:LastModifiedById>00528000003pbOYAAY</sf:LastModifiedById><sf:LastModifiedDate>2017-01-23T15:10:11.000Z</sf:LastModifiedDate><sf:LengthWithoutComments>-1</sf:LengthWithoutComments><sf:Name>FloChangeRequestLogicHandler</sf:Name><sf:NamespacePrefix>FLODocs</sf:NamespacePrefix><sf:Status>Active</sf:Status><sf:SystemModstamp>2017-04-25T16:18:45.000Z</sf:SystemModstamp></result><result xsi:type="sf:sObject"><sf:type>ApexClass</sf:type><sf:Id>01p2800000EmQxmAAF</sf:Id><sf:ApiVersion>34.0</sf:ApiVersion><sf:Body>(hidden)</sf:Body><sf:BodyCrc>-1</sf:BodyCrc><sf:CreatedById>00528000003pbOYAAY</sf:CreatedById><sf:CreatedDate>2017-01-23T15:10:12.000Z</sf:CreatedDate><sf:Id>01p2800000EmQxmAAF</sf:Id><sf:IsValid>true</sf:IsValid><sf:LastModifiedById>00528000003pbOYAAY</sf:LastModifiedById><sf:LastModifiedDate>2017-01-23T15:10:12.000Z</sf:LastModifiedDate><sf:LengthWithoutComments>-1</sf:LengthWithoutComments><sf:Name>FloMakeJoinBatch</sf:Name><sf:NamespacePrefix>FLODocs</sf:NamespacePrefix><sf:Status>Active</sf:Status><sf:SystemModstamp>2017-04-25T16:18:45.000Z</sf:SystemModstamp></result><result xsi:type="sf:sObject"><sf:type>ApexClass</sf:type><sf:Id>01p2800000EmQxOAAV</sf:Id><sf:ApiVersion>36.0</sf:ApiVersion><sf:Body>(hidden)</sf:Body><sf:BodyCrc>-1</sf:BodyCrc><sf:CreatedById>00528000003pbOYAAY</sf:CreatedById><sf:CreatedDate>2017-01-23T15:10:11.000Z</sf:CreatedDate><sf:Id>01p2800000EmQxOAAV</sf:Id><sf:IsValid>true</sf:IsValid><sf:LastModifiedById>00528000003pbOYAAY</sf:LastModifiedById><sf:LastModifiedDate>2017-01-23T15:10:11.000Z</sf:LastModifiedDate><sf:LengthWithoutComments>-1</sf:LengthWithoutComments><sf:Name>FloApexParserTest</sf:Name><sf:NamespacePrefix>FLODocs</sf:NamespacePrefix><sf:Status>Active</sf:Status><sf:SystemModstamp>2017-04-25T16:18:44.000Z</sf:SystemModstamp></result><result xsi:type="sf:sObject"><sf:type>ApexClass</sf:type><sf:Id>01p2800000EmQy0AAF</sf:Id><sf:ApiVersion>34.0</sf:ApiVersion><sf:Body>(hidden)</sf:Body><sf:BodyCrc>-1</sf:BodyCrc><sf:CreatedById>00528000003pbOYAAY</sf:CreatedById><sf:CreatedDate>2017-01-23T15:10:12.000Z</sf:CreatedDate><sf:Id>01p2800000EmQy0AAF</sf:Id><sf:IsValid>true</sf:IsValid><sf:LastModifiedById>00528000003pbOYAAY</sf:LastModifiedById><sf:LastModifiedDate>2017-01-23T15:10:12.000Z</sf:LastModifiedDate><sf:LengthWithoutComments>-1</sf:LengthWithoutComments><sf:Name>FloPuff</sf:Name><sf:NamespacePrefix>FLODocs</sf:NamespacePrefix><sf:Status>Active</sf:Status><sf:SystemModstamp>2017-04-25T16:18:47.000Z</sf:SystemModstamp></result><result xsi:type="sf:sObject"><sf:type>ApexClass</sf:type><sf:Id>01p2800000EmQyFAAV</sf:Id><sf:ApiVersion>34.0</sf:ApiVersion><sf:Body>(hidden)</sf:Body><sf:BodyCrc>-1</sf:BodyCrc><sf:CreatedById>00528000003pbOYAAY</sf:CreatedById><sf:CreatedDate>2017-01-23T15:10:13.000Z</sf:CreatedDate><sf:Id>01p2800000EmQyFAAV</sf:Id><sf:IsValid>true</sf:IsValid><sf:LastModifiedById>00528000003pbOYAAY</sf:LastModifiedById><sf:LastModifiedDate>2017-01-23T15:10:13.000Z</sf:LastModifiedDate><sf:LengthWithoutComments>-1</sf:LengthWithoutComments><sf:Name>FloZippexTests</sf:Name><sf:NamespacePrefix>FLODocs</sf:NamespacePrefix><sf:Status>Active</sf:Status><sf:SystemModstamp>2017-04-25T16:18:47.000Z</sf:SystemModstamp></result><result xsi:type="sf:sObject"><sf:type>ApexClass</sf:type><sf:Id>01p2800000EmQxlAAF</sf:Id><sf:ApiVersion>36.0</sf:ApiVersion><sf:Body>(hidden)</sf:Body><sf:BodyCrc>-1</sf:BodyCrc><sf:CreatedById>00528000003pbOYAAY</sf:CreatedById><sf:CreatedDate>2017-01-23T15:10:12.000Z</sf:CreatedDate><sf:Id>01p2800000EmQxlAAF</sf:Id><sf:IsValid>true</sf:IsValid><sf:LastModifiedById>00528000003pbOYAAY</sf:LastModifiedById><sf:LastModifiedDate>2017-01-23T15:10:12.000Z</sf:LastModifiedDate><sf:LengthWithoutComments>-1</sf:LengthWithoutComments><sf:Name>FloJunctionTriggerHandler</sf:Name><sf:NamespacePrefix>FLODocs</sf:NamespacePrefix><sf:Status>Active</sf:Status><sf:SystemModstamp>2017-04-25T16:18:45.000Z</sf:SystemModstamp></result><result xsi:type="sf:sObject"><sf:type>ApexClass</sf:type><sf:Id>01p2800000EmQxPAAV</sf:Id><sf:ApiVersion>34.0</sf:ApiVersion><sf:Body>/*
This file is generated and isn't the actual source code for this
managed global class.
This read-only file shows the class's global constructors,
methods, variables, and properties.
To enable code to compile, all methods return null.
*/
global class FloApproveRejectAndImpactAnalysisCR {
    global FloApproveRejectAndImpactAnalysisCR() {

    }
    webService static String approveUser(String crId) {
        return null;
    }
    webService static String impactAnalysis(String crId) {
        return null;
    }
    webService static String reject(String crId) {
        return null;
    }
}
</sf:Body><sf:BodyCrc>-1</sf:BodyCrc><sf:CreatedById>00528000003pbOYAAY</sf:CreatedById><sf:CreatedDate>2017-01-23T15:10:11.000Z</sf:CreatedDate><sf:Id>01p2800000EmQxPAAV</sf:Id><sf:IsValid>true</sf:IsValid><sf:LastModifiedById>00528000003pbOYAAY</sf:LastModifiedById><sf:LastModifiedDate>2017-01-23T15:10:11.000Z</sf:LastModifiedDate><sf:LengthWithoutComments>-1</sf:LengthWithoutComments><sf:Name>FloApproveRejectAndImpactAnalysisCR</sf:Name><sf:NamespacePrefix>FLODocs</sf:NamespacePrefix><sf:Status>Active</sf:Status><sf:SystemModstamp>2017-04-25T16:18:45.000Z</sf:SystemModstamp></result><result xsi:type="sf:sObject"><sf:type>ApexClass</sf:type><sf:Id>01p2800000EmQxsAAF</sf:Id><sf:ApiVersion>34.0</sf:ApiVersion><sf:Body>(hidden)</sf:Body><sf:BodyCrc>-1</sf:BodyCrc><sf:CreatedById>00528000003pbOYAAY</sf:CreatedById><sf:CreatedDate>2017-01-23T15:10:12.000Z</sf:CreatedDate><sf:Id>01p2800000EmQxsAAF</sf:Id><sf:IsValid>true</sf:IsValid><sf:LastModifiedById>00528000003pbOYAAY</sf:LastModifiedById><sf:LastModifiedDate>2017-01-23T15:10:12.000Z</sf:LastModifiedDate><sf:LengthWithoutComments>-1</sf:LengthWithoutComments><sf:Name>FloMetadataServiceTest</sf:Name><sf:NamespacePrefix>FLODocs</sf:NamespacePrefix><sf:Status>Active</sf:Status><sf:SystemModstamp>2017-04-25T16:18:46.000Z</sf:SystemModstamp></result><result xsi:type="sf:sObject"><sf:type>ApexClass</sf:type><sf:Id>01p2800000EmQxSAAV</sf:Id><sf:ApiVersion>34.0</sf:ApiVersion><sf:Body>/*
This file is generated and isn't the actual source code for this
managed global class.
This read-only file shows the class's global constructors,
methods, variables, and properties.
To enable code to compile, all methods return null.
*/
global class FloAutoScanner implements System.Schedulable {
    global FloAutoScanner() {

    }
    global void execute(System.SchedulableContext sc) {

    }
}
</sf:Body><sf:BodyCrc>-1</sf:BodyCrc><sf:CreatedById>00528000003pbOYAAY</sf:CreatedById><sf:CreatedDate>2017-01-23T15:10:11.000Z</sf:CreatedDate><sf:Id>01p2800000EmQxSAAV</sf:Id><sf:IsValid>true</sf:IsValid><sf:LastModifiedById>00528000003pbOYAAY</sf:LastModifiedById><sf:LastModifiedDate>2017-01-23T15:10:11.000Z</sf:LastModifiedDate><sf:LengthWithoutComments>-1</sf:LengthWithoutComments><sf:Name>FloAutoScanner</sf:Name><sf:NamespacePrefix>FLODocs</sf:NamespacePrefix><sf:Status>Active</sf:Status><sf:SystemModstamp>2017-04-25T16:18:45.000Z</sf:SystemModstamp></result><result xsi:type="sf:sObject"><sf:type>ApexClass</sf:type><sf:Id>01p2800000EmQxhAAF</sf:Id><sf:ApiVersion>34.0</sf:ApiVersion><sf:Body>(hidden)</sf:Body><sf:BodyCrc>-1</sf:BodyCrc><sf:CreatedById>00528000003pbOYAAY</sf:CreatedById><sf:CreatedDate>2017-01-23T15:10:11.000Z</sf:CreatedDate><sf:Id>01p2800000EmQxhAAF</sf:Id><sf:IsValid>true</sf:IsValid><sf:LastModifiedById>00528000003pbOYAAY</sf:LastModifiedById><sf:LastModifiedDate>2017-01-23T15:10:11.000Z</sf:LastModifiedDate><sf:LengthWithoutComments>-1</sf:LengthWithoutComments><sf:Name>FloFinderPdfController</sf:Name><sf:NamespacePrefix>FLODocs</sf:NamespacePrefix><sf:Status>Active</sf:Status><sf:SystemModstamp>2017-04-25T16:18:45.000Z</sf:SystemModstamp></result><result xsi:type="sf:sObject"><sf:type>ApexClass</sf:type><sf:Id>01p2800000EmN6TAAV</sf:Id><sf:ApiVersion>38.0</sf:ApiVersion><sf:Body>public interface TestInterface {
  String testMethodA();

}</sf:Body><sf:BodyCrc>2.074028333E9</sf:BodyCrc><sf:CreatedById>00528000003pbOYAAY</sf:CreatedById><sf:CreatedDate>2017-01-17T09:28:48.000Z</sf:CreatedDate><sf:Id>01p2800000EmN6TAAV</sf:Id><sf:IsValid>true</sf:IsValid><sf:LastModifiedById>00528000003pbOYAAY</sf:LastModifiedById><sf:LastModifiedDate>2017-01-17T09:29:05.000Z</sf:LastModifiedDate><sf:LengthWithoutComments>59</sf:LengthWithoutComments><sf:Name>TestInterface</sf:Name><sf:NamespacePrefix xsi:nil="true"/><sf:Status>Active</sf:Status><sf:SystemModstamp>2017-04-25T16:18:48.000Z</sf:SystemModstamp></result><result xsi:type="sf:sObject"><sf:type>ApexClass</sf:type><sf:Id>01p2800000EmQxNAAV</sf:Id><sf:ApiVersion>34.0</sf:ApiVersion><sf:Body>(hidden)</sf:Body><sf:BodyCrc>-1</sf:BodyCrc><sf:CreatedById>00528000003pbOYAAY</sf:CreatedById><sf:CreatedDate>2017-01-23T15:10:11.000Z</sf:CreatedDate><sf:Id>01p2800000EmQxNAAV</sf:Id><sf:IsValid>true</sf:IsValid><sf:LastModifiedById>00528000003pbOYAAY</sf:LastModifiedById><sf:LastModifiedDate>2017-01-23T15:10:11.000Z</sf:LastModifiedDate><sf:LengthWithoutComments>-1</sf:LengthWithoutComments><sf:Name>FloApexParserBatch</sf:Name><sf:NamespacePrefix>FLODocs</sf:NamespacePrefix><sf:Status>Active</sf:Status><sf:SystemModstamp>2017-04-25T16:18:44.000Z</sf:SystemModstamp></result><result xsi:type="sf:sObject"><sf:type>ApexClass</sf:type><sf:Id>01p2800000EmQxTAAV</sf:Id><sf:ApiVersion>34.0</sf:ApiVersion><sf:Body>(hidden)</sf:Body><sf:BodyCrc>-1</sf:BodyCrc><sf:CreatedById>00528000003pbOYAAY</sf:CreatedById><sf:CreatedDate>2017-01-23T15:10:11.000Z</sf:CreatedDate><sf:Id>01p2800000EmQxTAAV</sf:Id><sf:IsValid>true</sf:IsValid><sf:LastModifiedById>00528000003pbOYAAY</sf:LastModifiedById><sf:LastModifiedDate>2017-01-23T15:10:11.000Z</sf:LastModifiedDate><sf:LengthWithoutComments>-1</sf:LengthWithoutComments><sf:Name>FloChangeRequestEditNewController</sf:Name><sf:NamespacePrefix>FLODocs</sf:NamespacePrefix><sf:Status>Active</sf:Status><sf:SystemModstamp>2017-04-25T16:18:45.000Z</sf:SystemModstamp></result><result xsi:type="sf:sObject"><sf:type>ApexClass</sf:type><sf:Id>01p2800000EmQxjAAF</sf:Id><sf:ApiVersion>36.0</sf:ApiVersion><sf:Body>(hidden)</sf:Body><sf:BodyCrc>-1</sf:BodyCrc><sf:CreatedById>00528000003pbOYAAY</sf:CreatedById><sf:CreatedDate>2017-01-23T15:10:12.000Z</sf:CreatedDate><sf:Id>01p2800000EmQxjAAF</sf:Id><sf:IsValid>true</sf:IsValid><sf:LastModifiedById>00528000003pbOYAAY</sf:LastModifiedById><sf:LastModifiedDate>2017-01-23T15:10:12.000Z</sf:LastModifiedDate><sf:LengthWithoutComments>-1</sf:LengthWithoutComments><sf:Name>FloHexUtilTest</sf:Name><sf:NamespacePrefix>FLODocs</sf:NamespacePrefix><sf:Status>Active</sf:Status><sf:SystemModstamp>2017-04-25T16:18:45.000Z</sf:SystemModstamp></result><result xsi:type="sf:sObject"><sf:type>ApexClass</sf:type><sf:Id>01p2800000EmQxgAAF</sf:Id><sf:ApiVersion>34.0</sf:ApiVersion><sf:Body>(hidden)</sf:Body><sf:BodyCrc>-1</sf:BodyCrc><sf:CreatedById>00528000003pbOYAAY</sf:CreatedById><sf:CreatedDate>2017-01-23T15:10:11.000Z</sf:CreatedDate><sf:Id>01p2800000EmQxgAAF</sf:Id><sf:IsValid>true</sf:IsValid><sf:LastModifiedById>00528000003pbOYAAY</sf:LastModifiedById><sf:LastModifiedDate>2017-01-23T15:10:11.000Z</sf:LastModifiedDate><sf:LengthWithoutComments>-1</sf:LengthWithoutComments><sf:Name>FloFinderController</sf:Name><sf:NamespacePrefix>FLODocs</sf:NamespacePrefix><sf:Status>Active</sf:Status><sf:SystemModstamp>2017-04-25T16:18:45.000Z</sf:SystemModstamp></result><result xsi:type="sf:sObject"><sf:type>ApexClass</sf:type><sf:Id>01p2800000EmQy2AAF</sf:Id><sf:ApiVersion>34.0</sf:ApiVersion><sf:Body>/*
This file is generated and isn't the actual source code for this
managed global class.
This read-only file shows the class's global constructors,
methods, variables, and properties.
To enable code to compile, all methods return null.
*/
global class FloRemoteSiteHelperController {
    global static Exception LastMetadataAPIConnectionException {
        get;
    }
    global String rssNameString {
        get;
        set;
    }
    global FloRemoteSiteHelperController() {

    }
    global static Boolean checkMetadataAPIConnection() {
        return null;
    }
}
</sf:Body><sf:BodyCrc>-1</sf:BodyCrc><sf:CreatedById>00528000003pbOYAAY</sf:CreatedById><sf:CreatedDate>2017-01-23T15:10:12.000Z</sf:CreatedDate><sf:Id>01p2800000EmQy2AAF</sf:Id><sf:IsValid>true</sf:IsValid><sf:LastModifiedById>00528000003pbOYAAY</sf:LastModifiedById><sf:LastModifiedDate>2017-01-23T15:10:12.000Z</sf:LastModifiedDate><sf:LengthWithoutComments>-1</sf:LengthWithoutComments><sf:Name>FloRemoteSiteHelperController</sf:Name><sf:NamespacePrefix>FLODocs</sf:NamespacePrefix><sf:Status>Active</sf:Status><sf:SystemModstamp>2017-04-25T16:18:47.000Z</sf:SystemModstamp></result><result xsi:type="sf:sObject"><sf:type>ApexClass</sf:type><sf:Id>01p2800000EmN6nAAF</sf:Id><sf:ApiVersion>38.0</sf:ApiVersion><sf:Body>public class TestClassUsingClass2 extends TestAbstractClass{
    public override String absMethod() {
        return 'Hi';
    }
}</sf:Body><sf:BodyCrc>2.890514737E9</sf:BodyCrc><sf:CreatedById>00528000003pbOYAAY</sf:CreatedById><sf:CreatedDate>2017-01-17T09:32:45.000Z</sf:CreatedDate><sf:Id>01p2800000EmN6nAAF</sf:Id><sf:IsValid>true</sf:IsValid><sf:LastModifiedById>00528000003pbOYAAY</sf:LastModifiedById><sf:LastModifiedDate>2017-01-17T09:32:55.000Z</sf:LastModifiedDate><sf:LengthWithoutComments>131</sf:LengthWithoutComments><sf:Name>TestClassUsingClass2</sf:Name><sf:NamespacePrefix xsi:nil="true"/><sf:Status>Active</sf:Status><sf:SystemModstamp>2017-04-25T16:18:48.000Z</sf:SystemModstamp></result><result xsi:type="sf:sObject"><sf:type>ApexClass</sf:type><sf:Id>01p28000009g8RlAAI</sf:Id><sf:ApiVersion>27.0</sf:ApiVersion><sf:Body>public with sharing class WarehouseDataInstall {

    public WarehouseDataInstall() {}

    public static boolean getHasData() {
        return [SELECT Id from Merchandise__c].size() &gt; 0;
    }
    
    public PageReference createData() {
        List&lt;Merchandise__c&gt; m = new List&lt;Merchandise__c&gt;();
        m.add(new Merchandise__c(Name='Laptop',Price__c=500,Quantity__c=1000));
        m.add(new Merchandise__c(Name='Desktop',Price__c=1000,Quantity__c=500));
        m.add(new Merchandise__c(Name='Tablet',Price__c=300,Quantity__c=5000));
        m.add(new Merchandise__c(Name='Rack Server',Price__c=3245.99,Quantity__c=500));
        m.add(new Merchandise__c(Name='Old Laptop',Price__c=345.99,Quantity__c=50));
        m.add(new Merchandise__c(Name='Deluxe Desktop',Price__c=1399.99,Quantity__c=250));
        m.add(new Merchandise__c(Name='Work Desktop',Price__c=1145.99,Quantity__c=750));        
        insert m;
        
        for (Integer i=0; i&lt;=6; i++) {
            Invoice__c inv = new Invoice__c(Status__c=(i &lt; 3 ? 'Closed' : 'Open'));
            insert inv;
            
            Line_Item__c li = new Line_Item__c
              (Name='i', Quantity__c=1, Merchandise__c=m[i].Id,Invoice__c=inv.Id);
            insert li;       
        }
       
        
        return null;
    }
    
    
    @isTest
    public static void testWarehouseDataInstall() {
        WarehouseDataInstall wdi = new WarehouseDataInstall();
        if(!WarehouseDataInstall.getHasData()) {
            wdi.createData();
        }
        System.assertEquals(true,WarehouseDataInstall.getHasData());
    }

}</sf:Body><sf:BodyCrc>3.92028578E9</sf:BodyCrc><sf:CreatedById>00528000003pbOYAAY</sf:CreatedById><sf:CreatedDate>2016-07-20T21:30:30.000Z</sf:CreatedDate><sf:Id>01p28000009g8RlAAI</sf:Id><sf:IsValid>true</sf:IsValid><sf:LastModifiedById>00528000003pbOYAAY</sf:LastModifiedById><sf:LastModifiedDate>2016-07-20T21:30:30.000Z</sf:LastModifiedDate><sf:LengthWithoutComments>1550</sf:LengthWithoutComments><sf:Name>WarehouseDataInstall</sf:Name><sf:NamespacePrefix xsi:nil="true"/><sf:Status>Active</sf:Status><sf:SystemModstamp>2017-04-25T16:18:48.000Z</sf:SystemModstamp></result><result xsi:type="sf:sObject"><sf:type>ApexClass</sf:type><sf:Id>01p2800000EmQxpAAF</sf:Id><sf:ApiVersion>34.0</sf:ApiVersion><sf:Body>(hidden)</sf:Body><sf:BodyCrc>-1</sf:BodyCrc><sf:CreatedById>00528000003pbOYAAY</sf:CreatedById><sf:CreatedDate>2017-01-23T15:10:12.000Z</sf:CreatedDate><sf:Id>01p2800000EmQxpAAF</sf:Id><sf:IsValid>true</sf:IsValid><sf:LastModifiedById>00528000003pbOYAAY</sf:LastModifiedById><sf:LastModifiedDate>2017-01-23T15:10:12.000Z</sf:LastModifiedDate><sf:LengthWithoutComments>-1</sf:LengthWithoutComments><sf:Name>FloMakeJoinHandlerTest</sf:Name><sf:NamespacePrefix>FLODocs</sf:NamespacePrefix><sf:Status>Active</sf:Status><sf:SystemModstamp>2017-04-25T16:18:46.000Z</sf:SystemModstamp></result><result xsi:type="sf:sObject"><sf:type>ApexClass</sf:type><sf:Id>01p2800000EmQy3AAF</sf:Id><sf:ApiVersion>34.0</sf:ApiVersion><sf:Body>(hidden)</sf:Body><sf:BodyCrc>-1</sf:BodyCrc><sf:CreatedById>00528000003pbOYAAY</sf:CreatedById><sf:CreatedDate>2017-01-23T15:10:12.000Z</sf:CreatedDate><sf:Id>01p2800000EmQy3AAF</sf:Id><sf:IsValid>true</sf:IsValid><sf:LastModifiedById>00528000003pbOYAAY</sf:LastModifiedById><sf:LastModifiedDate>2017-01-23T15:10:12.000Z</sf:LastModifiedDate><sf:LengthWithoutComments>-1</sf:LengthWithoutComments><sf:Name>FloRemoteSitePageController</sf:Name><sf:NamespacePrefix>FLODocs</sf:NamespacePrefix><sf:Status>Active</sf:Status><sf:SystemModstamp>2017-04-25T16:18:47.000Z</sf:SystemModstamp></result><result xsi:type="sf:sObject"><sf:type>ApexClass</sf:type><sf:Id>01p2800000EmQyBAAV</sf:Id><sf:ApiVersion>34.0</sf:ApiVersion><sf:Body>(hidden)</sf:Body><sf:BodyCrc>-1</sf:BodyCrc><sf:CreatedById>00528000003pbOYAAY</sf:CreatedById><sf:CreatedDate>2017-01-23T15:10:13.000Z</sf:CreatedDate><sf:Id>01p2800000EmQyBAAV</sf:Id><sf:IsValid>true</sf:IsValid><sf:LastModifiedById>00528000003pbOYAAY</sf:LastModifiedById><sf:LastModifiedDate>2017-01-23T15:10:13.000Z</sf:LastModifiedDate><sf:LengthWithoutComments>-1</sf:LengthWithoutComments><sf:Name>FloSpiderFileBatch</sf:Name><sf:NamespacePrefix>FLODocs</sf:NamespacePrefix><sf:Status>Active</sf:Status><sf:SystemModstamp>2017-04-25T16:18:47.000Z</sf:SystemModstamp></result><result xsi:type="sf:sObject"><sf:type>ApexClass</sf:type><sf:Id>01p2800000EmQy8AAF</sf:Id><sf:ApiVersion>34.0</sf:ApiVersion><sf:Body>(hidden)</sf:Body><sf:BodyCrc>-1</sf:BodyCrc><sf:CreatedById>00528000003pbOYAAY</sf:CreatedById><sf:CreatedDate>2017-01-23T15:10:12.000Z</sf:CreatedDate><sf:Id>01p2800000EmQy8AAF</sf:Id><sf:IsValid>true</sf:IsValid><sf:LastModifiedById>00528000003pbOYAAY</sf:LastModifiedById><sf:LastModifiedDate>2017-01-23T15:10:12.000Z</sf:LastModifiedDate><sf:LengthWithoutComments>-1</sf:LengthWithoutComments><sf:Name>FloSpiderBatchHandler</sf:Name><sf:NamespacePrefix>FLODocs</sf:NamespacePrefix><sf:Status>Active</sf:Status><sf:SystemModstamp>2017-04-25T16:18:47.000Z</sf:SystemModstamp></result><result xsi:type="sf:sObject"><sf:type>ApexClass</sf:type><sf:Id>01p2800000EmQxQAAV</sf:Id><sf:ApiVersion>36.0</sf:ApiVersion><sf:Body>(hidden)</sf:Body><sf:BodyCrc>-1</sf:BodyCrc><sf:CreatedById>00528000003pbOYAAY</sf:CreatedById><sf:CreatedDate>2017-01-23T15:10:11.000Z</sf:CreatedDate><sf:Id>01p2800000EmQxQAAV</sf:Id><sf:IsValid>true</sf:IsValid><sf:LastModifiedById>00528000003pbOYAAY</sf:LastModifiedById><sf:LastModifiedDate>2017-01-23T15:10:11.000Z</sf:LastModifiedDate><sf:LengthWithoutComments>-1</sf:LengthWithoutComments><sf:Name>FloApproveRejectAndImpactAnalysisCRTest</sf:Name><sf:NamespacePrefix>FLODocs</sf:NamespacePrefix><sf:Status>Active</sf:Status><sf:SystemModstamp>2017-04-25T16:18:45.000Z</sf:SystemModstamp></result><result xsi:type="sf:sObject"><sf:type>ApexClass</sf:type><sf:Id>01p2800000EmQxbAAF</sf:Id><sf:ApiVersion>34.0</sf:ApiVersion><sf:Body>(hidden)</sf:Body><sf:BodyCrc>-1</sf:BodyCrc><sf:CreatedById>00528000003pbOYAAY</sf:CreatedById><sf:CreatedDate>2017-01-23T15:10:11.000Z</sf:CreatedDate><sf:Id>01p2800000EmQxbAAF</sf:Id><sf:IsValid>true</sf:IsValid><sf:LastModifiedById>00528000003pbOYAAY</sf:LastModifiedById><sf:LastModifiedDate>2017-01-23T15:10:11.000Z</sf:LastModifiedDate><sf:LengthWithoutComments>-1</sf:LengthWithoutComments><sf:Name>FloDemoCoverageTest</sf:Name><sf:NamespacePrefix>FLODocs</sf:NamespacePrefix><sf:Status>Active</sf:Status><sf:SystemModstamp>2017-04-25T16:18:45.000Z</sf:SystemModstamp></result><result xsi:type="sf:sObject"><sf:type>ApexClass</sf:type><sf:Id>01p2800000EmQxkAAF</sf:Id><sf:ApiVersion>34.0</sf:ApiVersion><sf:Body>(hidden)</sf:Body><sf:BodyCrc>-1</sf:BodyCrc><sf:CreatedById>00528000003pbOYAAY</sf:CreatedById><sf:CreatedDate>2017-01-23T15:10:12.000Z</sf:CreatedDate><sf:Id>01p2800000EmQxkAAF</sf:Id><sf:IsValid>true</sf:IsValid><sf:LastModifiedById>00528000003pbOYAAY</sf:LastModifiedById><sf:LastModifiedDate>2017-01-23T15:10:12.000Z</sf:LastModifiedDate><sf:LengthWithoutComments>-1</sf:LengthWithoutComments><sf:Name>FloImpactAnalysisCRSectionController</sf:Name><sf:NamespacePrefix>FLODocs</sf:NamespacePrefix><sf:Status>Active</sf:Status><sf:SystemModstamp>2017-04-25T16:18:45.000Z</sf:SystemModstamp></result><result xsi:type="sf:sObject"><sf:type>ApexClass</sf:type><sf:Id>01p2800000EmQy7AAF</sf:Id><sf:ApiVersion>34.0</sf:ApiVersion><sf:Body>(hidden)</sf:Body><sf:BodyCrc>-1</sf:BodyCrc><sf:CreatedById>00528000003pbOYAAY</sf:CreatedById><sf:CreatedDate>2017-01-23T15:10:12.000Z</sf:CreatedDate><sf:Id>01p2800000EmQy7AAF</sf:Id><sf:IsValid>true</sf:IsValid><sf:LastModifiedById>00528000003pbOYAAY</sf:LastModifiedById><sf:LastModifiedDate>2017-01-23T15:10:12.000Z</sf:LastModifiedDate><sf:LengthWithoutComments>-1</sf:LengthWithoutComments><sf:Name>FloScannerInitJob</sf:Name><sf:NamespacePrefix>FLODocs</sf:NamespacePrefix><sf:Status>Active</sf:Status><sf:SystemModstamp>2017-04-25T16:18:47.000Z</sf:SystemModstamp></result><result xsi:type="sf:sObject"><sf:type>ApexClass</sf:type><sf:Id>01p2800000EmQy4AAF</sf:Id><sf:ApiVersion>34.0</sf:ApiVersion><sf:Body>/*
This file is generated and isn't the actual source code for this
managed global class.
This read-only file shows the class's global constructors,
methods, variables, and properties.
To enable code to compile, all methods return null.
*/
global class FloRescannerNow {
    global FloRescannerNow() {

    }
    webService static String reScanner(String cId, Boolean isChangeRequest) {
        return null;
    }
}
</sf:Body><sf:BodyCrc>-1</sf:BodyCrc><sf:CreatedById>00528000003pbOYAAY</sf:CreatedById><sf:CreatedDate>2017-01-23T15:10:12.000Z</sf:CreatedDate><sf:Id>01p2800000EmQy4AAF</sf:Id><sf:IsValid>true</sf:IsValid><sf:LastModifiedById>00528000003pbOYAAY</sf:LastModifiedById><sf:LastModifiedDate>2017-01-23T15:10:12.000Z</sf:LastModifiedDate><sf:LengthWithoutComments>-1</sf:LengthWithoutComments><sf:Name>FloRescannerNow</sf:Name><sf:NamespacePrefix>FLODocs</sf:NamespacePrefix><sf:Status>Active</sf:Status><sf:SystemModstamp>2017-04-25T16:18:47.000Z</sf:SystemModstamp></result><result xsi:type="sf:sObject"><sf:type>ApexClass</sf:type><sf:Id>01p2800000EmQxeAAF</sf:Id><sf:ApiVersion>34.0</sf:ApiVersion><sf:Body>(hidden)</sf:Body><sf:BodyCrc>-1</sf:BodyCrc><sf:CreatedById>00528000003pbOYAAY</sf:CreatedById><sf:CreatedDate>2017-01-23T15:10:11.000Z</sf:CreatedDate><sf:Id>01p2800000EmQxeAAF</sf:Id><sf:IsValid>true</sf:IsValid><sf:LastModifiedById>00528000003pbOYAAY</sf:LastModifiedById><sf:LastModifiedDate>2017-01-23T15:10:11.000Z</sf:LastModifiedDate><sf:LengthWithoutComments>-1</sf:LengthWithoutComments><sf:Name>FloERDViewController</sf:Name><sf:NamespacePrefix>FLODocs</sf:NamespacePrefix><sf:Status>Active</sf:Status><sf:SystemModstamp>2017-04-25T16:18:45.000Z</sf:SystemModstamp></result><result xsi:type="sf:sObject"><sf:type>ApexClass</sf:type><sf:Id>01p2800000EmQxZAAV</sf:Id><sf:ApiVersion>34.0</sf:ApiVersion><sf:Body>/*
This file is generated and isn't the actual source code for this
managed global class.
This read-only file shows the class's global constructors,
methods, variables, and properties.
To enable code to compile, all methods return null.
*/
global class FloDateLastUsedBatch implements Database.Batchable&lt;SObject&gt; {
    global FloDateLastUsedBatch() {

    }
    global void execute(Database.BatchableContext BC, List&lt;SObject&gt; scope) {

    }
    global void finish(Database.BatchableContext BC) {

    }
    global Database.QueryLocator start(Database.BatchableContext BC) {
        return null;
    }
}
</sf:Body><sf:BodyCrc>-1</sf:BodyCrc><sf:CreatedById>00528000003pbOYAAY</sf:CreatedById><sf:CreatedDate>2017-01-23T15:10:11.000Z</sf:CreatedDate><sf:Id>01p2800000EmQxZAAV</sf:Id><sf:IsValid>true</sf:IsValid><sf:LastModifiedById>00528000003pbOYAAY</sf:LastModifiedById><sf:LastModifiedDate>2017-01-23T15:10:11.000Z</sf:LastModifiedDate><sf:LengthWithoutComments>-1</sf:LengthWithoutComments><sf:Name>FloDateLastUsedBatch</sf:Name><sf:NamespacePrefix>FLODocs</sf:NamespacePrefix><sf:Status>Active</sf:Status><sf:SystemModstamp>2017-04-25T16:18:45.000Z</sf:SystemModstamp></result><result xsi:type="sf:sObject"><sf:type>ApexClass</sf:type><sf:Id>01p2800000EmQy6AAF</sf:Id><sf:ApiVersion>34.0</sf:ApiVersion><sf:Body>(hidden)</sf:Body><sf:BodyCrc>-1</sf:BodyCrc><sf:CreatedById>00528000003pbOYAAY</sf:CreatedById><sf:CreatedDate>2017-01-23T15:10:12.000Z</sf:CreatedDate><sf:Id>01p2800000EmQy6AAF</sf:Id><sf:IsValid>true</sf:IsValid><sf:LastModifiedById>00528000003pbOYAAY</sf:LastModifiedById><sf:LastModifiedDate>2017-01-23T15:10:12.000Z</sf:LastModifiedDate><sf:LengthWithoutComments>-1</sf:LengthWithoutComments><sf:Name>FloScannerFilesUnread</sf:Name><sf:NamespacePrefix>FLODocs</sf:NamespacePrefix><sf:Status>Active</sf:Status><sf:SystemModstamp>2017-04-25T16:18:47.000Z</sf:SystemModstamp></result><result xsi:type="sf:sObject"><sf:type>ApexClass</sf:type><sf:Id>01p2800000EmQxxAAF</sf:Id><sf:ApiVersion>36.0</sf:ApiVersion><sf:Body>(hidden)</sf:Body><sf:BodyCrc>-1</sf:BodyCrc><sf:CreatedById>00528000003pbOYAAY</sf:CreatedById><sf:CreatedDate>2017-01-23T15:10:12.000Z</sf:CreatedDate><sf:Id>01p2800000EmQxxAAF</sf:Id><sf:IsValid>true</sf:IsValid><sf:LastModifiedById>00528000003pbOYAAY</sf:LastModifiedById><sf:LastModifiedDate>2017-01-23T15:10:12.000Z</sf:LastModifiedDate><sf:LengthWithoutComments>-1</sf:LengthWithoutComments><sf:Name>FloProcessEditNewControllerTest</sf:Name><sf:NamespacePrefix>FLODocs</sf:NamespacePrefix><sf:Status>Active</sf:Status><sf:SystemModstamp>2017-04-25T16:18:47.000Z</sf:SystemModstamp></result><result xsi:type="sf:sObject"><sf:type>ApexClass</sf:type><sf:Id>01p2800000EmQyAAAV</sf:Id><sf:ApiVersion>34.0</sf:ApiVersion><sf:Body>(hidden)</sf:Body><sf:BodyCrc>-1</sf:BodyCrc><sf:CreatedById>00528000003pbOYAAY</sf:CreatedById><sf:CreatedDate>2017-01-23T15:10:12.000Z</sf:CreatedDate><sf:Id>01p2800000EmQyAAAV</sf:Id><sf:IsValid>true</sf:IsValid><sf:LastModifiedById>00528000003pbOYAAY</sf:LastModifiedById><sf:LastModifiedDate>2017-01-23T15:10:12.000Z</sf:LastModifiedDate><sf:LengthWithoutComments>-1</sf:LengthWithoutComments><sf:Name>FloSpiderController</sf:Name><sf:NamespacePrefix>FLODocs</sf:NamespacePrefix><sf:Status>Active</sf:Status><sf:SystemModstamp>2017-04-25T16:18:47.000Z</sf:SystemModstamp></result><result xsi:type="sf:sObject"><sf:type>ApexClass</sf:type><sf:Id>01p2800000EmQxYAAV</sf:Id><sf:ApiVersion>36.0</sf:ApiVersion><sf:Body>(hidden)</sf:Body><sf:BodyCrc>-1</sf:BodyCrc><sf:CreatedById>00528000003pbOYAAY</sf:CreatedById><sf:CreatedDate>2017-01-23T15:10:11.000Z</sf:CreatedDate><sf:Id>01p2800000EmQxYAAV</sf:Id><sf:IsValid>true</sf:IsValid><sf:LastModifiedById>00528000003pbOYAAY</sf:LastModifiedById><sf:LastModifiedDate>2017-01-23T15:10:11.000Z</sf:LastModifiedDate><sf:LengthWithoutComments>-1</sf:LengthWithoutComments><sf:Name>FloCleanMakeJoinDateTest</sf:Name><sf:NamespacePrefix>FLODocs</sf:NamespacePrefix><sf:Status>Active</sf:Status><sf:SystemModstamp>2017-04-25T16:18:45.000Z</sf:SystemModstamp></result><result xsi:type="sf:sObject"><sf:type>ApexClass</sf:type><sf:Id>01p2800000EmQxnAAF</sf:Id><sf:ApiVersion>38.0</sf:ApiVersion><sf:Body>(hidden)</sf:Body><sf:BodyCrc>-1</sf:BodyCrc><sf:CreatedById>00528000003pbOYAAY</sf:CreatedById><sf:CreatedDate>2017-01-23T15:10:12.000Z</sf:CreatedDate><sf:Id>01p2800000EmQxnAAF</sf:Id><sf:IsValid>true</sf:IsValid><sf:LastModifiedById>00528000003pbOYAAY</sf:LastModifiedById><sf:LastModifiedDate>2017-01-23T15:10:12.000Z</sf:LastModifiedDate><sf:LengthWithoutComments>-1</sf:LengthWithoutComments><sf:Name>FloMakeJoinHandler</sf:Name><sf:NamespacePrefix>FLODocs</sf:NamespacePrefix><sf:Status>Active</sf:Status><sf:SystemModstamp>2017-04-25T16:18:45.000Z</sf:SystemModstamp></result><result xsi:type="sf:sObject"><sf:type>ApexClass</sf:type><sf:Id>01p2800000EmQyCAAV</sf:Id><sf:ApiVersion>34.0</sf:ApiVersion><sf:Body>(hidden)</sf:Body><sf:BodyCrc>-1</sf:BodyCrc><sf:CreatedById>00528000003pbOYAAY</sf:CreatedById><sf:CreatedDate>2017-01-23T15:10:13.000Z</sf:CreatedDate><sf:Id>01p2800000EmQyCAAV</sf:Id><sf:IsValid>true</sf:IsValid><sf:LastModifiedById>00528000003pbOYAAY</sf:LastModifiedById><sf:LastModifiedDate>2017-01-23T15:10:13.000Z</sf:LastModifiedDate><sf:LengthWithoutComments>-1</sf:LengthWithoutComments><sf:Name>FloSpiderFileBatchTest</sf:Name><sf:NamespacePrefix>FLODocs</sf:NamespacePrefix><sf:Status>Active</sf:Status><sf:SystemModstamp>2017-04-25T16:18:47.000Z</sf:SystemModstamp></result><result xsi:type="sf:sObject"><sf:type>ApexClass</sf:type><sf:Id>01p2800000EmQxrAAF</sf:Id><sf:ApiVersion>34.0</sf:ApiVersion><sf:Body>(hidden)</sf:Body><sf:BodyCrc>-1</sf:BodyCrc><sf:CreatedById>00528000003pbOYAAY</sf:CreatedById><sf:CreatedDate>2017-01-23T15:10:12.000Z</sf:CreatedDate><sf:Id>01p2800000EmQxrAAF</sf:Id><sf:IsValid>true</sf:IsValid><sf:LastModifiedById>00528000003pbOYAAY</sf:LastModifiedById><sf:LastModifiedDate>2017-01-23T15:10:12.000Z</sf:LastModifiedDate><sf:LengthWithoutComments>-1</sf:LengthWithoutComments><sf:Name>FloMetadataService</sf:Name><sf:NamespacePrefix>FLODocs</sf:NamespacePrefix><sf:Status>Active</sf:Status><sf:SystemModstamp>2017-04-25T16:18:46.000Z</sf:SystemModstamp></result><result xsi:type="sf:sObject"><sf:type>ApexClass</sf:type><sf:Id>01p2800000EmQxwAAF</sf:Id><sf:ApiVersion>36.0</sf:ApiVersion><sf:Body>(hidden)</sf:Body><sf:BodyCrc>-1</sf:BodyCrc><sf:CreatedById>00528000003pbOYAAY</sf:CreatedById><sf:CreatedDate>2017-01-23T15:10:12.000Z</sf:CreatedDate><sf:Id>01p2800000EmQxwAAF</sf:Id><sf:IsValid>true</sf:IsValid><sf:LastModifiedById>00528000003pbOYAAY</sf:LastModifiedById><sf:LastModifiedDate>2017-01-23T15:10:12.000Z</sf:LastModifiedDate><sf:LengthWithoutComments>-1</sf:LengthWithoutComments><sf:Name>FloProcessEditNewController</sf:Name><sf:NamespacePrefix>FLODocs</sf:NamespacePrefix><sf:Status>Active</sf:Status><sf:SystemModstamp>2017-04-25T16:18:47.000Z</sf:SystemModstamp></result><result xsi:type="sf:sObject"><sf:type>ApexClass</sf:type><sf:Id>01p2800000EmQy9AAF</sf:Id><sf:ApiVersion>36.0</sf:ApiVersion><sf:Body>(hidden)</sf:Body><sf:BodyCrc>-1</sf:BodyCrc><sf:CreatedById>00528000003pbOYAAY</sf:CreatedById><sf:CreatedDate>2017-01-23T15:10:12.000Z</sf:CreatedDate><sf:Id>01p2800000EmQy9AAF</sf:Id><sf:IsValid>true</sf:IsValid><sf:LastModifiedById>00528000003pbOYAAY</sf:LastModifiedById><sf:LastModifiedDate>2017-01-23T15:10:12.000Z</sf:LastModifiedDate><sf:LengthWithoutComments>-1</sf:LengthWithoutComments><sf:Name>FloSpiderBatchHandlerTest</sf:Name><sf:NamespacePrefix>FLODocs</sf:NamespacePrefix><sf:Status>Active</sf:Status><sf:SystemModstamp>2017-04-25T16:18:47.000Z</sf:SystemModstamp></result><result xsi:type="sf:sObject"><sf:type>ApexClass</sf:type><sf:Id>01p2800000EmQxfAAF</sf:Id><sf:ApiVersion>36.0</sf:ApiVersion><sf:Body>(hidden)</sf:Body><sf:BodyCrc>-1</sf:BodyCrc><sf:CreatedById>00528000003pbOYAAY</sf:CreatedById><sf:CreatedDate>2017-01-23T15:10:11.000Z</sf:CreatedDate><sf:Id>01p2800000EmQxfAAF</sf:Id><sf:IsValid>true</sf:IsValid><sf:LastModifiedById>00528000003pbOYAAY</sf:LastModifiedById><sf:LastModifiedDate>2017-01-23T15:10:11.000Z</sf:LastModifiedDate><sf:LengthWithoutComments>-1</sf:LengthWithoutComments><sf:Name>FloERDViewControllerTest</sf:Name><sf:NamespacePrefix>FLODocs</sf:NamespacePrefix><sf:Status>Active</sf:Status><sf:SystemModstamp>2017-04-25T16:18:45.000Z</sf:SystemModstamp></result><result xsi:type="sf:sObject"><sf:type>ApexClass</sf:type><sf:Id>01p2800000EmQxRAAV</sf:Id><sf:ApiVersion>34.0</sf:ApiVersion><sf:Body>(hidden)</sf:Body><sf:BodyCrc>-1</sf:BodyCrc><sf:CreatedById>00528000003pbOYAAY</sf:CreatedById><sf:CreatedDate>2017-01-23T15:10:11.000Z</sf:CreatedDate><sf:Id>01p2800000EmQxRAAV</sf:Id><sf:IsValid>true</sf:IsValid><sf:LastModifiedById>00528000003pbOYAAY</sf:LastModifiedById><sf:LastModifiedDate>2017-01-23T15:10:11.000Z</sf:LastModifiedDate><sf:LengthWithoutComments>-1</sf:LengthWithoutComments><sf:Name>FloAttachmentCustomizationTest</sf:Name><sf:NamespacePrefix>FLODocs</sf:NamespacePrefix><sf:Status>Active</sf:Status><sf:SystemModstamp>2017-04-25T16:18:45.000Z</sf:SystemModstamp></result><result xsi:type="sf:sObject"><sf:type>ApexClass</sf:type><sf:Id>01p2800000EmQyDAAV</sf:Id><sf:ApiVersion>34.0</sf:ApiVersion><sf:Body>(hidden)</sf:Body><sf:BodyCrc>-1</sf:BodyCrc><sf:CreatedById>00528000003pbOYAAY</sf:CreatedById><sf:CreatedDate>2017-01-23T15:10:13.000Z</sf:CreatedDate><sf:Id>01p2800000EmQyDAAV</sf:Id><sf:IsValid>true</sf:IsValid><sf:LastModifiedById>00528000003pbOYAAY</sf:LastModifiedById><sf:LastModifiedDate>2017-01-23T15:10:13.000Z</sf:LastModifiedDate><sf:LengthWithoutComments>-1</sf:LengthWithoutComments><sf:Name>FloUtils</sf:Name><sf:NamespacePrefix>FLODocs</sf:NamespacePrefix><sf:Status>Active</sf:Status><sf:SystemModstamp>2017-04-25T16:18:47.000Z</sf:SystemModstamp></result><result xsi:type="sf:sObject"><sf:type>ApexClass</sf:type><sf:Id>01p2800000EmN5zAAF</sf:Id><sf:ApiVersion>38.0</sf:ApiVersion><sf:Body>public abstract class TestAbstractClass {
    public TestAbstractClass(){}
    public abstract String absMethod();
}</sf:Body><sf:BodyCrc>1.618384202E9</sf:BodyCrc><sf:CreatedById>00528000003pbOYAAY</sf:CreatedById><sf:CreatedDate>2017-01-17T09:20:00.000Z</sf:CreatedDate><sf:Id>01p2800000EmN5zAAF</sf:Id><sf:IsValid>true</sf:IsValid><sf:LastModifiedById>00528000003pbOYAAY</sf:LastModifiedById><sf:LastModifiedDate>2017-01-17T09:20:13.000Z</sf:LastModifiedDate><sf:LengthWithoutComments>117</sf:LengthWithoutComments><sf:Name>TestAbstractClass</sf:Name><sf:NamespacePrefix xsi:nil="true"/><sf:Status>Active</sf:Status><sf:SystemModstamp>2017-04-25T16:18:47.000Z</sf:SystemModstamp></result><result xsi:type="sf:sObject"><sf:type>ApexClass</sf:type><sf:Id>01p2800000EmQxvAAF</sf:Id><sf:ApiVersion>34.0</sf:ApiVersion><sf:Body>(hidden)</sf:Body><sf:BodyCrc>-1</sf:BodyCrc><sf:CreatedById>00528000003pbOYAAY</sf:CreatedById><sf:CreatedDate>2017-01-23T15:10:12.000Z</sf:CreatedDate><sf:Id>01p2800000EmQxvAAF</sf:Id><sf:IsValid>true</sf:IsValid><sf:LastModifiedById>00528000003pbOYAAY</sf:LastModifiedById><sf:LastModifiedDate>2017-01-23T15:10:12.000Z</sf:LastModifiedDate><sf:LengthWithoutComments>-1</sf:LengthWithoutComments><sf:Name>FloPoliciesAndChangeRequestHandler</sf:Name><sf:NamespacePrefix>FLODocs</sf:NamespacePrefix><sf:Status>Active</sf:Status><sf:SystemModstamp>2017-04-25T16:18:47.000Z</sf:SystemModstamp></result><result xsi:type="sf:sObject"><sf:type>ApexClass</sf:type><sf:Id>01p2800000EmN6iAAF</sf:Id><sf:ApiVersion>38.0</sf:ApiVersion><sf:Body>public class TestStaticUtils {
	public static final String TEST = 'Test';
    public static void testStatic() {}
}</sf:Body><sf:BodyCrc>2.718891609E9</sf:BodyCrc><sf:CreatedById>00528000003pbOYAAY</sf:CreatedById><sf:CreatedDate>2017-01-17T09:30:34.000Z</sf:CreatedDate><sf:Id>01p2800000EmN6iAAF</sf:Id><sf:IsValid>true</sf:IsValid><sf:LastModifiedById>00528000003pbOYAAY</sf:LastModifiedById><sf:LastModifiedDate>2017-01-17T09:31:59.000Z</sf:LastModifiedDate><sf:LengthWithoutComments>115</sf:LengthWithoutComments><sf:Name>TestStaticUtils</sf:Name><sf:NamespacePrefix xsi:nil="true"/><sf:Status>Active</sf:Status><sf:SystemModstamp>2017-04-25T16:18:48.000Z</sf:SystemModstamp></result><result xsi:type="sf:sObject"><sf:type>ApexClass</sf:type><sf:Id>01p2800000EmQxyAAF</sf:Id><sf:ApiVersion>34.0</sf:ApiVersion><sf:Body>(hidden)</sf:Body><sf:BodyCrc>-1</sf:BodyCrc><sf:CreatedById>00528000003pbOYAAY</sf:CreatedById><sf:CreatedDate>2017-01-23T15:10:12.000Z</sf:CreatedDate><sf:Id>01p2800000EmQxyAAF</sf:Id><sf:IsValid>true</sf:IsValid><sf:LastModifiedById>00528000003pbOYAAY</sf:LastModifiedById><sf:LastModifiedDate>2017-01-23T15:10:12.000Z</sf:LastModifiedDate><sf:LengthWithoutComments>-1</sf:LengthWithoutComments><sf:Name>FloProcessIssueEditNewController</sf:Name><sf:NamespacePrefix>FLODocs</sf:NamespacePrefix><sf:Status>Active</sf:Status><sf:SystemModstamp>2017-04-25T16:18:47.000Z</sf:SystemModstamp></result><result xsi:type="sf:sObject"><sf:type>ApexClass</sf:type><sf:Id>01p2800000EmQxiAAF</sf:Id><sf:ApiVersion>34.0</sf:ApiVersion><sf:Body>(hidden)</sf:Body><sf:BodyCrc>-1</sf:BodyCrc><sf:CreatedById>00528000003pbOYAAY</sf:CreatedById><sf:CreatedDate>2017-01-23T15:10:12.000Z</sf:CreatedDate><sf:Id>01p2800000EmQxiAAF</sf:Id><sf:IsValid>true</sf:IsValid><sf:LastModifiedById>00528000003pbOYAAY</sf:LastModifiedById><sf:LastModifiedDate>2017-01-23T15:10:12.000Z</sf:LastModifiedDate><sf:LengthWithoutComments>-1</sf:LengthWithoutComments><sf:Name>FloHexUtil</sf:Name><sf:NamespacePrefix>FLODocs</sf:NamespacePrefix><sf:Status>Active</sf:Status><sf:SystemModstamp>2017-04-25T16:18:45.000Z</sf:SystemModstamp></result><result xsi:type="sf:sObject"><sf:type>ApexClass</sf:type><sf:Id>01p2800000EmN6OAAV</sf:Id><sf:ApiVersion>38.0</sf:ApiVersion><sf:Body>public class TestClass {
    public static void setTestObjDate(TestObject__c obj) {
        obj.CustomDate__c = Date.today();
    }
    
    
    public static void setTestObjText(TestObject__c obj) {
        obj.CustomText__c = 'New Object';
    }
}</sf:Body><sf:BodyCrc>2.24676179E8</sf:BodyCrc><sf:CreatedById>00528000003pbOYAAY</sf:CreatedById><sf:CreatedDate>2017-01-17T09:23:11.000Z</sf:CreatedDate><sf:Id>01p2800000EmN6OAAV</sf:Id><sf:IsValid>true</sf:IsValid><sf:LastModifiedById>00528000003pbOYAAY</sf:LastModifiedById><sf:LastModifiedDate>2017-01-17T09:27:52.000Z</sf:LastModifiedDate><sf:LengthWithoutComments>241</sf:LengthWithoutComments><sf:Name>TestClass</sf:Name><sf:NamespacePrefix xsi:nil="true"/><sf:Status>Active</sf:Status><sf:SystemModstamp>2017-04-25T16:18:48.000Z</sf:SystemModstamp></result><result xsi:type="sf:sObject"><sf:type>ApexClass</sf:type><sf:Id>01p2800000EmQxqAAF</sf:Id><sf:ApiVersion>34.0</sf:ApiVersion><sf:Body>/*
This file is generated and isn't the actual source code for this
managed global class.
This read-only file shows the class's global constructors,
methods, variables, and properties.
To enable code to compile, all methods return null.
*/
global class FloMakeJoinSchedulableinterface implements System.Schedulable {
    global void execute(System.SchedulableContext sc) {

    }
}
</sf:Body><sf:BodyCrc>-1</sf:BodyCrc><sf:CreatedById>00528000003pbOYAAY</sf:CreatedById><sf:CreatedDate>2017-01-23T15:10:12.000Z</sf:CreatedDate><sf:Id>01p2800000EmQxqAAF</sf:Id><sf:IsValid>true</sf:IsValid><sf:LastModifiedById>00528000003pbOYAAY</sf:LastModifiedById><sf:LastModifiedDate>2017-01-23T15:10:12.000Z</sf:LastModifiedDate><sf:LengthWithoutComments>-1</sf:LengthWithoutComments><sf:Name>FloMakeJoinSchedulableinterface</sf:Name><sf:NamespacePrefix>FLODocs</sf:NamespacePrefix><sf:Status>Active</sf:Status><sf:SystemModstamp>2017-04-25T16:18:46.000Z</sf:SystemModstamp></result><result xsi:type="sf:sObject"><sf:type>ApexClass</sf:type><sf:Id>01p2800000EmQxWAAV</sf:Id><sf:ApiVersion>34.0</sf:ApiVersion><sf:Body>(hidden)</sf:Body><sf:BodyCrc>-1</sf:BodyCrc><sf:CreatedById>00528000003pbOYAAY</sf:CreatedById><sf:CreatedDate>2017-01-23T15:10:11.000Z</sf:CreatedDate><sf:Id>01p2800000EmQxWAAV</sf:Id><sf:IsValid>true</sf:IsValid><sf:LastModifiedById>00528000003pbOYAAY</sf:LastModifiedById><sf:LastModifiedDate>2017-01-23T15:10:11.000Z</sf:LastModifiedDate><sf:LengthWithoutComments>-1</sf:LengthWithoutComments><sf:Name>FloChangeRequestLogicHandlerTest</sf:Name><sf:NamespacePrefix>FLODocs</sf:NamespacePrefix><sf:Status>Active</sf:Status><sf:SystemModstamp>2017-04-25T16:18:45.000Z</sf:SystemModstamp></result><result xsi:type="sf:sObject"><sf:type>ApexClass</sf:type><sf:Id>01p2800000EmQxdAAF</sf:Id><sf:ApiVersion>38.0</sf:ApiVersion><sf:Body>(hidden)</sf:Body><sf:BodyCrc>-1</sf:BodyCrc><sf:CreatedById>00528000003pbOYAAY</sf:CreatedById><sf:CreatedDate>2017-01-23T15:10:11.000Z</sf:CreatedDate><sf:Id>01p2800000EmQxdAAF</sf:Id><sf:IsValid>true</sf:IsValid><sf:LastModifiedById>00528000003pbOYAAY</sf:LastModifiedById><sf:LastModifiedDate>2017-01-23T15:10:11.000Z</sf:LastModifiedDate><sf:LengthWithoutComments>-1</sf:LengthWithoutComments><sf:Name>FloDocsLinksControllerTest</sf:Name><sf:NamespacePrefix>FLODocs</sf:NamespacePrefix><sf:Status>Active</sf:Status><sf:SystemModstamp>2017-04-25T16:18:45.000Z</sf:SystemModstamp></result><result xsi:type="sf:sObject"><sf:type>ApexClass</sf:type><sf:Id>01p28000009hASiAAM</sf:Id><sf:ApiVersion>37.0</sf:ApiVersion><sf:Body>@RestResource(urlMapping='/Cases/*')
global with sharing class CaseManager {

    @HttpGet
    global static Case getCaseById() {
        RestRequest request = RestContext.request;
        // grab the caseId from the end of the URL
        String caseId = request.requestURI.substring(
          request.requestURI.lastIndexOf('/')+1);
        Case result =  [SELECT CaseNumber,Subject,Status,Origin,Priority
                        FROM Case
                        WHERE Id = :caseId];
        return result;
    }

    @HttpPost
    global static ID createCase(String subject, String status,
        String origin, String priority) {
        Case thisCase = new Case(
            Subject=subject,
            Status=status,
            Origin=origin,
            Priority=priority);
        insert thisCase;
        return thisCase.Id;
    }   

    @HttpDelete
    global static void deleteCase() {
        RestRequest request = RestContext.request;
        String caseId = request.requestURI.substring(
            request.requestURI.lastIndexOf('/')+1);
        Case thisCase = [SELECT Id FROM Case WHERE Id = :caseId];
        delete thisCase;
    }     

    @HttpPut
    global static ID upsertCase(String subject, String status,
        String origin, String priority, String id) {
        Case thisCase = new Case(
                Id=id,
                Subject=subject,
                Status=status,
                Origin=origin,
                Priority=priority);
        // Match case by Id, if present.
        // Otherwise, create new case.
        upsert thisCase;
        // Return the case ID.
        return thisCase.Id;
    }

    @HttpPatch
    global static ID updateCaseFields() {
        RestRequest request = RestContext.request;
        String caseId = request.requestURI.substring(
            request.requestURI.lastIndexOf('/')+1);
        Case thisCase = [SELECT Id FROM Case WHERE Id = :caseId];
        // Deserialize the JSON string into name-value pairs
        Map&lt;String, Object&gt; params = (Map&lt;String, Object&gt;)JSON.deserializeUntyped(request.requestbody.tostring());
        // Iterate through each parameter field and value
        for(String fieldName : params.keySet()) {
            // Set the field and value on the Case sObject
            thisCase.put(fieldName, params.get(fieldName));
        }
        update thisCase;
        return thisCase.Id;
    }    

}</sf:Body><sf:BodyCrc>3.05314064E8</sf:BodyCrc><sf:CreatedById>00528000003pbOYAAY</sf:CreatedById><sf:CreatedDate>2016-07-28T08:58:31.000Z</sf:CreatedDate><sf:Id>01p28000009hASiAAM</sf:Id><sf:IsValid>true</sf:IsValid><sf:LastModifiedById>00528000003pbOYAAY</sf:LastModifiedById><sf:LastModifiedDate>2016-07-28T08:59:14.000Z</sf:LastModifiedDate><sf:LengthWithoutComments>2064</sf:LengthWithoutComments><sf:Name>CaseManager</sf:Name><sf:NamespacePrefix xsi:nil="true"/><sf:Status>Active</sf:Status><sf:SystemModstamp>2017-04-25T16:18:44.000Z</sf:SystemModstamp></result><result xsi:type="sf:sObject"><sf:type>ApexClass</sf:type><sf:Id>01p2800000EmQxtAAF</sf:Id><sf:ApiVersion>34.0</sf:ApiVersion><sf:Body>(hidden)</sf:Body><sf:BodyCrc>-1</sf:BodyCrc><sf:CreatedById>00528000003pbOYAAY</sf:CreatedById><sf:CreatedDate>2017-01-23T15:10:12.000Z</sf:CreatedDate><sf:Id>01p2800000EmQxtAAF</sf:Id><sf:IsValid>true</sf:IsValid><sf:LastModifiedById>00528000003pbOYAAY</sf:LastModifiedById><sf:LastModifiedDate>2017-01-23T15:10:12.000Z</sf:LastModifiedDate><sf:LengthWithoutComments>-1</sf:LengthWithoutComments><sf:Name>FloMultiSelectListController</sf:Name><sf:NamespacePrefix>FLODocs</sf:NamespacePrefix><sf:Status>Active</sf:Status><sf:SystemModstamp>2017-04-25T16:18:46.000Z</sf:SystemModstamp></result><result xsi:type="sf:sObject"><sf:type>ApexClass</sf:type><sf:Id>01p2800000EmQy5AAF</sf:Id><sf:ApiVersion>34.0</sf:ApiVersion><sf:Body>(hidden)</sf:Body><sf:BodyCrc>-1</sf:BodyCrc><sf:CreatedById>00528000003pbOYAAY</sf:CreatedById><sf:CreatedDate>2017-01-23T15:10:12.000Z</sf:CreatedDate><sf:Id>01p2800000EmQy5AAF</sf:Id><sf:IsValid>true</sf:IsValid><sf:LastModifiedById>00528000003pbOYAAY</sf:LastModifiedById><sf:LastModifiedDate>2017-01-23T15:10:12.000Z</sf:LastModifiedDate><sf:LengthWithoutComments>-1</sf:LengthWithoutComments><sf:Name>FloRetrieveMetadataJob</sf:Name><sf:NamespacePrefix>FLODocs</sf:NamespacePrefix><sf:Status>Active</sf:Status><sf:SystemModstamp>2017-04-25T16:18:47.000Z</sf:SystemModstamp></result></retrieveResponse></soapenv:Body></soapenv:Envelope>